linsolve/__init__.py
linsolve/_version.py
linsolve/linsolve.py
linsolve/version.py
linsolve-1.1.5.dist-info/LICENSE
linsolve-1.1.5.dist-info/METADATA
linsolve-1.1.5.dist-info/WHEEL
linsolve-1.1.5.dist-info/top_level.txt
linsolve-1.1.5.dist-info/RECORD
