Metadata-Version: 2.1
Name: linsolve
Version: 1.1.5
Summary: high-level tools for linearizing and solving systems of equations
Author: HERA Team
License: MIT License
Project-URL: Repository, https://github.com/HERA-Team/linsolve
Keywords: linear equations,optimal estimation
Classifier: Development Status :: 5 - Production/Stable
Classifier: Intended Audience :: Science/Research
Classifier: License :: OSI Approved :: BSD License
Classifier: Programming Language :: Python :: 3
Classifier: Programming Language :: Python :: 3.9
Classifier: Programming Language :: Python :: 3.10
Classifier: Programming Language :: Python :: 3.11
Classifier: Programming Language :: Python :: 3.12
Classifier: Topic :: Scientific/Engineering :: Mathematics
Requires-Python: >=3.7
License-File: LICENSE
Requires-Dist: numpy >=1.23
Requires-Dist: scipy
Provides-Extra: dev
Requires-Dist: pre-commit ; extra == 'dev'
Requires-Dist: linsolve[test] ; extra == 'dev'
Provides-Extra: test
Requires-Dist: pytest ; extra == 'test'
Requires-Dist: pytest-cov ; extra == 'test'
